[
  {
    "type": "감사헌금",
    "memberId": 1757223155161,
    "amount": 10000,
    "date": "2025-09-07",
    "memo": "",
    "id": 1757238197109,
    "recordedAt": "2025-09-07T09:43:17.109Z"
  },
  {
    "type": "선교헌금",
    "memberId": 1757223137129,
    "amount": 25000,
    "date": "2025-09-07",
    "memo": "",
    "id": 1757238237707,
    "recordedAt": "2025-09-07T09:43:57.707Z"
  },
  {
    "type": "감사헌금",
    "memberId": 1757223181685,
    "amount": 5000,
    "date": "2025-09-07",
    "memo": "",
    "id": 1757240001276,
    "recordedAt": "2025-09-07T10:13:21.276Z"
  }
]